{
    "_links": {
        "self": {
            "href": "/jenkins/view/zeus_recycle/job/zeus_creative_recycles/6400/wfapi/describe"
        }
    },
    "durationMillis": 12251682,
    "endTimeMillis": 1530680080793,
    "id": "6400",
    "name": "#6400",
    "pauseDurationMillis": 0,
    "queueDurationMillis": 34,
    "stages": [
        {
            "_links": {
                "self": {
                    "href": "/jenkins/view/zeus_recycle/job/zeus_creative_recycles/6400/execution/node/6/wfapi/describe"
                }
            },
            "durationMillis": 29998,
            "execNode": "",
            "id": "6",
            "name": "prepare",
            "pauseDurationMillis": 0,
            "startTimeMillis": 1530667898417,
            "status": "SUCCESS"
        },
        {
            "_links": {
                "self": {
                    "href": "/jenkins/view/zeus_recycle/job/zeus_creative_recycles/6400/execution/node/25/wfapi/describe"
                }
            },
            "durationMillis": 645,
            "execNode": "",
            "id": "25",
            "name": "Updated Environemnt ID",
            "pauseDurationMillis": 0,
            "startTimeMillis": 1530667928435,
            "status": "SUCCESS"
        },
        {
            "_links": {
                "self": {
                    "href": "/jenkins/view/zeus_recycle/job/zeus_creative_recycles/6400/execution/node/34/wfapi/describe"
                }
            },
            "durationMillis": 94,
            "execNode": "",
            "id": "34",
            "name": "Update Custom Date",
            "pauseDurationMillis": 0,
            "startTimeMillis": 1530667929089,
            "status": "NOT_EXECUTED"
        },
        {
            "_links": {
                "self": {
                    "href": "/jenkins/view/zeus_recycle/job/zeus_creative_recycles/6400/execution/node/38/wfapi/describe"
                }
            },
            "durationMillis": 3554137,
            "execNode": "",
            "id": "38",
            "name": "SiteDB data_load",
            "pauseDurationMillis": 0,
            "startTimeMillis": 1530667929192,
            "status": "SUCCESS"
        },
        {
            "_links": {
                "self": {
                    "href": "/jenkins/view/zeus_recycle/job/zeus_creative_recycles/6400/execution/node/51/wfapi/describe"
                }
            },
            "durationMillis": 128478,
            "execNode": "",
            "id": "51",
            "name": "Recycle Apollo",
            "pauseDurationMillis": 0,
            "startTimeMillis": 1530671483337,
            "status": "SUCCESS"
        },
        {
            "_links": {
                "self": {
                    "href": "/jenkins/view/zeus_recycle/job/zeus_creative_recycles/6400/execution/node/64/wfapi/describe"
                }
            },
            "durationMillis": 3258589,
            "execNode": "",
            "id": "64",
            "name": "Recycle FCC",
            "pauseDurationMillis": 0,
            "startTimeMillis": 1530671611825,
            "status": "SUCCESS"
        },
        {
            "_links": {
                "self": {
                    "href": "/jenkins/view/zeus_recycle/job/zeus_creative_recycles/6400/execution/node/77/wfapi/describe"
                }
            },
            "durationMillis": 488048,
            "execNode": "",
            "id": "77",
            "name": "Recycle Discovery",
            "pauseDurationMillis": 0,
            "startTimeMillis": 1530674870423,
            "status": "SUCCESS"
        },
        {
            "_links": {
                "self": {
                    "href": "/jenkins/view/zeus_recycle/job/zeus_creative_recycles/6400/execution/node/90/wfapi/describe"
                }
            },
            "durationMillis": 756478,
            "execNode": "",
            "id": "90",
            "name": "SCP and RDPP artifact check  and download",
            "pauseDurationMillis": 0,
            "startTimeMillis": 1530675358480,
            "status": "SUCCESS"
        },
        {
            "_links": {
                "self": {
                    "href": "/jenkins/view/zeus_recycle/job/zeus_creative_recycles/6400/execution/node/115/wfapi/describe"
                }
            },
            "durationMillis": 916959,
            "execNode": "",
            "id": "115",
            "name": "Run SCP and RDPP and Catalog Review load",
            "pauseDurationMillis": 0,
            "startTimeMillis": 1530676114967,
            "status": "SUCCESS"
        },
        {
            "_links": {
                "self": {
                    "href": "/jenkins/view/zeus_recycle/job/zeus_creative_recycles/6400/execution/node/128/wfapi/describe"
                }
            },
            "durationMillis": 195223,
            "execNode": "",
            "id": "128",
            "name": "Recycle Content",
            "pauseDurationMillis": 0,
            "startTimeMillis": 1530677031934,
            "status": "SUCCESS"
        },
        {
            "_links": {
                "self": {
                    "href": "/jenkins/view/zeus_recycle/job/zeus_creative_recycles/6400/execution/node/141/wfapi/describe"
                }
            },
            "durationMillis": 2233956,
            "execNode": "",
            "id": "141",
            "name": "Run Apollo Indexing, Content preload and SCP Exchange rate",
            "pauseDurationMillis": 0,
            "startTimeMillis": 1530677227165,
            "status": "SUCCESS"
        },
        {
            "_links": {
                "self": {
                    "href": "/jenkins/view/zeus_recycle/job/zeus_creative_recycles/6400/execution/node/154/wfapi/describe"
                }
            },
            "durationMillis": 35,
            "execNode": "",
            "id": "154",
            "name": "Recycle",
            "pauseDurationMillis": 0,
            "startTimeMillis": 1530679461129,
            "status": "SUCCESS"
        },
        {
            "_links": {
                "self": {
                    "href": "/jenkins/view/zeus_recycle/job/zeus_creative_recycles/6400/execution/node/162/wfapi/describe"
                }
            },
            "durationMillis": 183786,
            "execNode": "",
            "id": "162",
            "name": "Recycle Customer",
            "pauseDurationMillis": 0,
            "startTimeMillis": 1530679461164,
            "status": "SUCCESS"
        },
        {
            "_links": {
                "self": {
                    "href": "/jenkins/view/zeus_recycle/job/zeus_creative_recycles/6400/execution/node/164/wfapi/describe"
                }
            },
            "durationMillis": 187436,
            "execNode": "",
            "id": "164",
            "name": "Recycle Order",
            "pauseDurationMillis": 0,
            "startTimeMillis": 1530679461167,
            "status": "SUCCESS"
        },
        {
            "_links": {
                "self": {
                    "href": "/jenkins/view/zeus_recycle/job/zeus_creative_recycles/6400/execution/node/166/wfapi/describe"
                }
            },
            "durationMillis": 97400,
            "execNode": "",
            "id": "166",
            "name": "Recycle Promotion",
            "pauseDurationMillis": 0,
            "startTimeMillis": 1530679461170,
            "status": "SUCCESS"
        },
        {
            "_links": {
                "self": {
                    "href": "/jenkins/view/zeus_recycle/job/zeus_creative_recycles/6400/execution/node/207/wfapi/describe"
                }
            },
            "durationMillis": 32,
            "execNode": "",
            "id": "207",
            "name": "Recycle web",
            "pauseDurationMillis": 0,
            "startTimeMillis": 1530679648706,
            "status": "SUCCESS"
        },
        {
            "_links": {
                "self": {
                    "href": "/jenkins/view/zeus_recycle/job/zeus_creative_recycles/6400/execution/node/213/wfapi/describe"
                }
            },
            "durationMillis": 431675,
            "execNode": "",
            "id": "213",
            "name": "Recycle WSSG",
            "pauseDurationMillis": 0,
            "startTimeMillis": 1530679648738,
            "status": "SUCCESS"
        },
        {
            "_links": {
                "self": {
                    "href": "/jenkins/view/zeus_recycle/job/zeus_creative_recycles/6400/execution/node/215/wfapi/describe"
                }
            },
            "durationMillis": 431812,
            "execNode": "",
            "id": "215",
            "name": "Recycle NavApp",
            "pauseDurationMillis": 0,
            "startTimeMillis": 1530679648741,
            "status": "SUCCESS"
        },
        {
            "_links": {
                "self": {
                    "href": "/jenkins/view/zeus_recycle/job/zeus_creative_recycles/6400/execution/node/244/wfapi/describe"
                }
            },
            "durationMillis": 140,
            "execNode": "",
            "id": "244",
            "name": "Declarative: Post Actions",
            "pauseDurationMillis": 0,
            "startTimeMillis": 1530680080617,
            "status": "SUCCESS"
        }
    ],
    "startTimeMillis": 1530667829111,
    "status": "SUCCESS"
}
